Metadata-Version: 1.0
Name: lucidcache
Version: 1.0
Summary: Simple Python library for caching functions' output
Home-page: UNKNOWN
Author: Kaletise
Author-email: admin@kaletise.me
License: MIT
Platform: UNKNOWN
